{
    "project": {},
    "files": {
        "build\\gallery-io-utils\\gallery-io-utils-debug.js": {
            "name": "build\\gallery-io-utils\\gallery-io-utils-debug.js",
            "modules": {
                "io-extras": 1
            },
            "classes": {},
            "fors": {
                "io": 1
            },
            "namespaces": {}
        },
        "build\\gallery-io-utils\\gallery-io-utils.js": {
            "name": "build\\gallery-io-utils\\gallery-io-utils.js",
            "modules": {},
            "classes": {},
            "fors": {
                "io": 1
            },
            "namespaces": {}
        },
        "js\\io-utils.js": {
            "name": "js\\io-utils.js",
            "modules": {},
            "classes": {},
            "fors": {
                "io": 1
            },
            "namespaces": {}
        }
    },
    "modules": {
        "io-extras": {
            "name": "io-extras",
            "submodules": {},
            "classes": {
                "io": 1
            },
            "fors": {
                "io": 1
            },
            "namespaces": {},
            "tag": "module",
            "file": "build\\gallery-io-utils\\gallery-io-utils-debug.js",
            "line": 3,
            "description": "Promise based methods for performing IO requests."
        }
    },
    "classes": {
        "io": {
            "name": "io",
            "shortname": "io",
            "classitems": [],
            "plugins": [],
            "extensions": [],
            "plugin_for": [],
            "extension_for": [],
            "module": "io-extras",
            "namespace": ""
        }
    },
    "classitems": [
        {
            "file": "build\\gallery-io-utils\\gallery-io-utils-debug.js",
            "line": 9,
            "description": "Method for initiating an ajax call.",
            "itemtype": "method",
            "name": "xhr",
            "static": 1,
            "params": [
                {
                    "name": "uri",
                    "description": "Qualified path to transaction resource.",
                    "type": "String"
                },
                {
                    "name": "options",
                    "description": "Configuration object for the transaction.",
                    "type": "Object",
                    "optional": true,
                    "props": [
                        {
                            "name": "method",
                            "description": "HTTP method verb (e.g., GET or POST).",
                            "type": "String",
                            "optional": true,
                            "optdefault": "GET"
                        },
                        {
                            "name": "data",
                            "description": "This is the name-value string that will be\n    sent as the transaction data. If the request is HTTP GET, the data become\n    part of querystring. If HTTP POST, the data are sent in the message body.",
                            "type": "Object|String",
                            "optional": true
                        },
                        {
                            "name": "form",
                            "description": "Form serialization configuration object. Its properties\n    are:\n    * `id` node object or id of HTML form\n    * `useDisabled` true to also serialize disabled form field values (defaults\n        to false)",
                            "type": "Object",
                            "optional": true
                        },
                        {
                            "name": "headers",
                            "description": "Object map of transaction headers to send to\n    the server. The object keys are the header names and the values are the\n    header values.",
                            "type": "Object",
                            "optional": true
                        },
                        {
                            "name": "timeout",
                            "description": "Millisecond threshold for the transaction\n    before being automatically aborted.",
                            "type": "Number",
                            "optional": true
                        }
                    ]
                }
            ],
            "return": {
                "description": "Promise for the response object. Contains an extra\n    `abort()` method to cancel the request.",
                "type": "Promise"
            },
            "class": "io",
            "module": "io-extras"
        },
        {
            "file": "build\\gallery-io-utils\\gallery-io-utils-debug.js",
            "line": 61,
            "description": "Initiaites an AJAX call with the HTTP method GET.",
            "itemtype": "method",
            "name": "get",
            "static": 1,
            "params": [
                {
                    "name": "uri",
                    "description": "Qualified path to transaction resource.",
                    "type": "String"
                },
                {
                    "name": "options",
                    "description": "Same configuration options as Y.io.xhr()",
                    "type": "Object",
                    "optional": true
                }
            ],
            "return": {
                "description": "Promise for the response object. Contains an extra\n    `abort()` method to cancel the request.",
                "type": "Promise"
            },
            "class": "io",
            "module": "io-extras"
        },
        {
            "file": "build\\gallery-io-utils\\gallery-io-utils-debug.js",
            "line": 72,
            "description": "Initiaites an AJAX call with the HTTP method POST.",
            "itemtype": "method",
            "name": "post",
            "static": 1,
            "params": [
                {
                    "name": "uri",
                    "description": "Qualified path to transaction resource.",
                    "type": "String"
                },
                {
                    "name": "options",
                    "description": "Same configuration options as Y.io.xhr()",
                    "type": "Object",
                    "optional": true
                }
            ],
            "return": {
                "description": "Promise for the response object. Contains an extra\n    `abort()` method to cancel the request.",
                "type": "Promise"
            },
            "class": "io",
            "module": "io-extras"
        },
        {
            "file": "build\\gallery-io-utils\\gallery-io-utils-debug.js",
            "line": 83,
            "description": "Initiaites an AJAX call with the HTTP method PUT.",
            "itemtype": "method",
            "name": "put",
            "static": 1,
            "params": [
                {
                    "name": "uri",
                    "description": "Qualified path to transaction resource.",
                    "type": "String"
                },
                {
                    "name": "options",
                    "description": "Same configuration options as Y.io.xhr()",
                    "type": "Object",
                    "optional": true
                }
            ],
            "return": {
                "description": "Promise for the response object. Contains an extra\n    `abort()` method to cancel the request.",
                "type": "Promise"
            },
            "class": "io",
            "module": "io-extras"
        },
        {
            "file": "build\\gallery-io-utils\\gallery-io-utils-debug.js",
            "line": 94,
            "description": "Initiaites an AJAX call with the HTTP method DELETE.",
            "itemtype": "method",
            "name": "delete",
            "static": 1,
            "params": [
                {
                    "name": "uri",
                    "description": "Qualified path to transaction resource.",
                    "type": "String"
                },
                {
                    "name": "options",
                    "description": "Same configuration options as Y.io.xhr()",
                    "type": "Object",
                    "optional": true
                }
            ],
            "return": {
                "description": "Promise for the response object. Contains an extra\n    `abort()` method to cancel the request.",
                "type": "Promise"
            },
            "class": "io",
            "module": "io-extras"
        },
        {
            "file": "build\\gallery-io-utils\\gallery-io-utils-debug.js",
            "line": 114,
            "description": "Alias for Y.io.delete()",
            "itemtype": "method",
            "name": "DELETE",
            "static": 1,
            "class": "io",
            "module": "io-extras"
        },
        {
            "file": "build\\gallery-io-utils\\gallery-io-utils-debug.js",
            "line": 123,
            "description": "Initiaites an AJAX call with the HTTP method POST and sends the data contained\nin the specified form element.",
            "itemtype": "method",
            "name": "postForm",
            "static": 1,
            "params": [
                {
                    "name": "uri",
                    "description": "Qualified path to transaction resource.",
                    "type": "String"
                },
                {
                    "name": "selector",
                    "description": "CSS selector or Y.Node instance pointing to a form\n    element.",
                    "type": "String|Node"
                },
                {
                    "name": "options",
                    "description": "Same configuration options as Y.io.xhr()",
                    "type": "Object",
                    "optional": true
                }
            ],
            "return": {
                "description": "Promise for the response object. Contains an extra\n    `abort()` method to cancel the request.",
                "type": "Promise"
            },
            "class": "io",
            "module": "io-extras"
        },
        {
            "file": "build\\gallery-io-utils\\gallery-io-utils-debug.js",
            "line": 148,
            "description": "Inserts one or more scripts tags.",
            "itemtype": "method",
            "name": "script",
            "static": 1,
            "params": [
                {
                    "name": "uri",
                    "description": "Path or array of paths to the scripts.",
                    "type": "String|String[]"
                },
                {
                    "name": "options",
                    "description": "Configuration options",
                    "type": "Object",
                    "optional": true
                }
            ],
            "return": {
                "description": "Promise for the response object.",
                "type": "Promise"
            },
            "class": "io",
            "module": "io-extras"
        },
        {
            "file": "build\\gallery-io-utils\\gallery-io-utils-debug.js",
            "line": 158,
            "description": "Inserts one or more CSS files into the page.",
            "itemtype": "method",
            "name": "css",
            "static": 1,
            "params": [
                {
                    "name": "uri",
                    "description": "Path or array of paths to the CSS files.",
                    "type": "String|String[]"
                },
                {
                    "name": "options",
                    "description": "Configuration options",
                    "type": "Object",
                    "optional": true
                }
            ],
            "return": {
                "description": "Promise for the response object.",
                "type": "Promise"
            },
            "class": "io",
            "module": "io-extras"
        },
        {
            "file": "build\\gallery-io-utils\\gallery-io-utils-debug.js",
            "line": 182,
            "description": "Performs a JSONP request. Requires the JSONP module.",
            "itemtype": "method",
            "name": "jsonp",
            "static": 1,
            "params": [
                {
                    "name": "uri",
                    "description": "The url of the JSONP service with the {callback}\n    placeholder where the callback function name typically goes",
                    "type": "String"
                },
                {
                    "name": "options",
                    "description": "Configuration options for the request",
                    "type": "Object",
                    "optional": true,
                    "props": [
                        {
                            "name": "timeout",
                            "description": "Millisecond threshold for the transaction\n    before being automatically aborted",
                            "type": "Number",
                            "optional": true
                        },
                        {
                            "name": "format",
                            "description": "Preprocessor function to stitch together\n    the supplied URL (first argument), the proxy function name (internally\n    generated), and any additional arguments passed to JSONPRequest#send()",
                            "type": "Function",
                            "optional": true
                        }
                    ]
                }
            ],
            "return": {
                "description": "Promise for the response object.",
                "type": "Promise"
            },
            "class": "io",
            "module": "io-extras"
        },
        {
            "file": "build\\gallery-io-utils\\gallery-io-utils-debug.js",
            "line": 221,
            "description": "Performs an AJAX request and parses the response as JSON notation.\nRequires the JSON module.",
            "itemtype": "method",
            "name": "json",
            "static": 1,
            "params": [
                {
                    "name": "uri",
                    "description": "Qualified path to transaction resource.",
                    "type": "String"
                },
                {
                    "name": "options",
                    "description": "Same configuration options as Y.io.xhr()",
                    "type": "Object",
                    "optional": true
                }
            ],
            "return": {
                "description": "Promise for the response object. Contains an extra\n    `abort()` method to cancel the request.",
                "type": "Promise"
            },
            "class": "io",
            "module": "io-extras"
        },
        {
            "file": "build\\gallery-io-utils\\gallery-io-utils-debug.js",
            "line": 244,
            "description": "Performs an AJAX request with the GET HTTP method and parses the response as\nJSON notation. Requires the JSON module.",
            "itemtype": "method",
            "name": "getJSON",
            "static": 1,
            "params": [
                {
                    "name": "uri",
                    "description": "Qualified path to transaction resource.",
                    "type": "String"
                },
                {
                    "name": "options",
                    "description": "Same configuration options as Y.io.xhr()",
                    "type": "Object",
                    "optional": true
                }
            ],
            "return": {
                "description": "Promise for the response object. Contains an extra\n    `abort()` method to cancel the request.",
                "type": "Promise"
            },
            "class": "io",
            "module": "io-extras"
        },
        {
            "file": "build\\gallery-io-utils\\gallery-io-utils-debug.js",
            "line": 256,
            "description": "Performs an AJAX request with the POST HTTP method and parses the response as\nJSON notation. Requires the JSON module.",
            "itemtype": "method",
            "name": "postJSON",
            "static": 1,
            "params": [
                {
                    "name": "uri",
                    "description": "Qualified path to transaction resource.",
                    "type": "String"
                },
                {
                    "name": "options",
                    "description": "Same configuration options as Y.io.xhr()",
                    "type": "Object",
                    "optional": true
                }
            ],
            "return": {
                "description": "Promise for the response object. Contains an extra\n    `abort()` method to cancel the request.",
                "type": "Promise"
            },
            "class": "io",
            "module": "io-extras"
        },
        {
            "file": "build\\gallery-io-utils\\gallery-io-utils-debug.js",
            "line": 268,
            "description": "Performs an AJAX request with the PUT HTTP method and parses the response as\nJSON notation. Requires the JSON module.",
            "itemtype": "method",
            "name": "putJSON",
            "static": 1,
            "params": [
                {
                    "name": "uri",
                    "description": "Qualified path to transaction resource.",
                    "type": "String"
                },
                {
                    "name": "options",
                    "description": "Same configuration options as Y.io.xhr()",
                    "type": "Object",
                    "optional": true
                }
            ],
            "return": {
                "description": "Promise for the response object. Contains an extra\n    `abort()` method to cancel the request.",
                "type": "Promise"
            },
            "class": "io",
            "module": "io-extras"
        },
        {
            "file": "build\\gallery-io-utils\\gallery-io-utils-debug.js",
            "line": 280,
            "description": "Performs an AJAX request with the DELETE HTTP method and parses the response as\nJSON notation. Requires the JSON module.",
            "itemtype": "method",
            "name": "deleteJSON",
            "static": 1,
            "params": [
                {
                    "name": "uri",
                    "description": "Qualified path to transaction resource.",
                    "type": "String"
                },
                {
                    "name": "options",
                    "description": "Same configuration options as Y.io.xhr()",
                    "type": "Object",
                    "optional": true
                }
            ],
            "return": {
                "description": "Promise for the response object. Contains an extra\n    `abort()` method to cancel the request.",
                "type": "Promise"
            },
            "class": "io",
            "module": "io-extras"
        },
        {
            "file": "build\\gallery-io-utils\\gallery-io-utils.js",
            "line": 9,
            "description": "Method for initiating an ajax call.",
            "itemtype": "method",
            "name": "xhr",
            "static": 1,
            "params": [
                {
                    "name": "uri",
                    "description": "Qualified path to transaction resource.",
                    "type": "String"
                },
                {
                    "name": "options",
                    "description": "Configuration object for the transaction.",
                    "type": "Object",
                    "optional": true,
                    "props": [
                        {
                            "name": "method",
                            "description": "HTTP method verb (e.g., GET or POST).",
                            "type": "String",
                            "optional": true,
                            "optdefault": "GET"
                        },
                        {
                            "name": "data",
                            "description": "This is the name-value string that will be\n    sent as the transaction data. If the request is HTTP GET, the data become\n    part of querystring. If HTTP POST, the data are sent in the message body.",
                            "type": "Object|String",
                            "optional": true
                        },
                        {
                            "name": "form",
                            "description": "Form serialization configuration object. Its properties\n    are:\n    * `id` node object or id of HTML form\n    * `useDisabled` true to also serialize disabled form field values (defaults\n        to false)",
                            "type": "Object",
                            "optional": true
                        },
                        {
                            "name": "headers",
                            "description": "Object map of transaction headers to send to\n    the server. The object keys are the header names and the values are the\n    header values.",
                            "type": "Object",
                            "optional": true
                        },
                        {
                            "name": "timeout",
                            "description": "Millisecond threshold for the transaction\n    before being automatically aborted.",
                            "type": "Number",
                            "optional": true
                        }
                    ]
                }
            ],
            "return": {
                "description": "Promise for the response object. Contains an extra\n    `abort()` method to cancel the request.",
                "type": "Promise"
            },
            "class": "io",
            "module": "io-extras"
        },
        {
            "file": "build\\gallery-io-utils\\gallery-io-utils.js",
            "line": 61,
            "description": "Initiaites an AJAX call with the HTTP method GET.",
            "itemtype": "method",
            "name": "get",
            "static": 1,
            "params": [
                {
                    "name": "uri",
                    "description": "Qualified path to transaction resource.",
                    "type": "String"
                },
                {
                    "name": "options",
                    "description": "Same configuration options as Y.io.xhr()",
                    "type": "Object",
                    "optional": true
                }
            ],
            "return": {
                "description": "Promise for the response object. Contains an extra\n    `abort()` method to cancel the request.",
                "type": "Promise"
            },
            "class": "io",
            "module": "io-extras"
        },
        {
            "file": "build\\gallery-io-utils\\gallery-io-utils.js",
            "line": 72,
            "description": "Initiaites an AJAX call with the HTTP method POST.",
            "itemtype": "method",
            "name": "post",
            "static": 1,
            "params": [
                {
                    "name": "uri",
                    "description": "Qualified path to transaction resource.",
                    "type": "String"
                },
                {
                    "name": "options",
                    "description": "Same configuration options as Y.io.xhr()",
                    "type": "Object",
                    "optional": true
                }
            ],
            "return": {
                "description": "Promise for the response object. Contains an extra\n    `abort()` method to cancel the request.",
                "type": "Promise"
            },
            "class": "io",
            "module": "io-extras"
        },
        {
            "file": "build\\gallery-io-utils\\gallery-io-utils.js",
            "line": 83,
            "description": "Initiaites an AJAX call with the HTTP method PUT.",
            "itemtype": "method",
            "name": "put",
            "static": 1,
            "params": [
                {
                    "name": "uri",
                    "description": "Qualified path to transaction resource.",
                    "type": "String"
                },
                {
                    "name": "options",
                    "description": "Same configuration options as Y.io.xhr()",
                    "type": "Object",
                    "optional": true
                }
            ],
            "return": {
                "description": "Promise for the response object. Contains an extra\n    `abort()` method to cancel the request.",
                "type": "Promise"
            },
            "class": "io",
            "module": "io-extras"
        },
        {
            "file": "build\\gallery-io-utils\\gallery-io-utils.js",
            "line": 94,
            "description": "Initiaites an AJAX call with the HTTP method DELETE.",
            "itemtype": "method",
            "name": "delete",
            "static": 1,
            "params": [
                {
                    "name": "uri",
                    "description": "Qualified path to transaction resource.",
                    "type": "String"
                },
                {
                    "name": "options",
                    "description": "Same configuration options as Y.io.xhr()",
                    "type": "Object",
                    "optional": true
                }
            ],
            "return": {
                "description": "Promise for the response object. Contains an extra\n    `abort()` method to cancel the request.",
                "type": "Promise"
            },
            "class": "io",
            "module": "io-extras"
        },
        {
            "file": "build\\gallery-io-utils\\gallery-io-utils.js",
            "line": 114,
            "description": "Alias for Y.io.delete()",
            "itemtype": "method",
            "name": "DELETE",
            "static": 1,
            "class": "io",
            "module": "io-extras"
        },
        {
            "file": "build\\gallery-io-utils\\gallery-io-utils.js",
            "line": 123,
            "description": "Initiaites an AJAX call with the HTTP method POST and sends the data contained\nin the specified form element.",
            "itemtype": "method",
            "name": "postForm",
            "static": 1,
            "params": [
                {
                    "name": "uri",
                    "description": "Qualified path to transaction resource.",
                    "type": "String"
                },
                {
                    "name": "selector",
                    "description": "CSS selector or Y.Node instance pointing to a form\n    element.",
                    "type": "String|Node"
                },
                {
                    "name": "options",
                    "description": "Same configuration options as Y.io.xhr()",
                    "type": "Object",
                    "optional": true
                }
            ],
            "return": {
                "description": "Promise for the response object. Contains an extra\n    `abort()` method to cancel the request.",
                "type": "Promise"
            },
            "class": "io",
            "module": "io-extras"
        },
        {
            "file": "build\\gallery-io-utils\\gallery-io-utils.js",
            "line": 148,
            "description": "Inserts one or more scripts tags.",
            "itemtype": "method",
            "name": "script",
            "static": 1,
            "params": [
                {
                    "name": "uri",
                    "description": "Path or array of paths to the scripts.",
                    "type": "String|String[]"
                },
                {
                    "name": "options",
                    "description": "Configuration options",
                    "type": "Object",
                    "optional": true
                }
            ],
            "return": {
                "description": "Promise for the response object.",
                "type": "Promise"
            },
            "class": "io",
            "module": "io-extras"
        },
        {
            "file": "build\\gallery-io-utils\\gallery-io-utils.js",
            "line": 158,
            "description": "Inserts one or more CSS files into the page.",
            "itemtype": "method",
            "name": "css",
            "static": 1,
            "params": [
                {
                    "name": "uri",
                    "description": "Path or array of paths to the CSS files.",
                    "type": "String|String[]"
                },
                {
                    "name": "options",
                    "description": "Configuration options",
                    "type": "Object",
                    "optional": true
                }
            ],
            "return": {
                "description": "Promise for the response object.",
                "type": "Promise"
            },
            "class": "io",
            "module": "io-extras"
        },
        {
            "file": "build\\gallery-io-utils\\gallery-io-utils.js",
            "line": 182,
            "description": "Performs a JSONP request. Requires the JSONP module.",
            "itemtype": "method",
            "name": "jsonp",
            "static": 1,
            "params": [
                {
                    "name": "uri",
                    "description": "The url of the JSONP service with the {callback}\n    placeholder where the callback function name typically goes",
                    "type": "String"
                },
                {
                    "name": "options",
                    "description": "Configuration options for the request",
                    "type": "Object",
                    "optional": true,
                    "props": [
                        {
                            "name": "timeout",
                            "description": "Millisecond threshold for the transaction\n    before being automatically aborted",
                            "type": "Number",
                            "optional": true
                        },
                        {
                            "name": "format",
                            "description": "Preprocessor function to stitch together\n    the supplied URL (first argument), the proxy function name (internally\n    generated), and any additional arguments passed to JSONPRequest#send()",
                            "type": "Function",
                            "optional": true
                        }
                    ]
                }
            ],
            "return": {
                "description": "Promise for the response object.",
                "type": "Promise"
            },
            "class": "io",
            "module": "io-extras"
        },
        {
            "file": "build\\gallery-io-utils\\gallery-io-utils.js",
            "line": 221,
            "description": "Performs an AJAX request and parses the response as JSON notation.\nRequires the JSON module.",
            "itemtype": "method",
            "name": "json",
            "static": 1,
            "params": [
                {
                    "name": "uri",
                    "description": "Qualified path to transaction resource.",
                    "type": "String"
                },
                {
                    "name": "options",
                    "description": "Same configuration options as Y.io.xhr()",
                    "type": "Object",
                    "optional": true
                }
            ],
            "return": {
                "description": "Promise for the response object. Contains an extra\n    `abort()` method to cancel the request.",
                "type": "Promise"
            },
            "class": "io",
            "module": "io-extras"
        },
        {
            "file": "build\\gallery-io-utils\\gallery-io-utils.js",
            "line": 244,
            "description": "Performs an AJAX request with the GET HTTP method and parses the response as\nJSON notation. Requires the JSON module.",
            "itemtype": "method",
            "name": "getJSON",
            "static": 1,
            "params": [
                {
                    "name": "uri",
                    "description": "Qualified path to transaction resource.",
                    "type": "String"
                },
                {
                    "name": "options",
                    "description": "Same configuration options as Y.io.xhr()",
                    "type": "Object",
                    "optional": true
                }
            ],
            "return": {
                "description": "Promise for the response object. Contains an extra\n    `abort()` method to cancel the request.",
                "type": "Promise"
            },
            "class": "io",
            "module": "io-extras"
        },
        {
            "file": "build\\gallery-io-utils\\gallery-io-utils.js",
            "line": 256,
            "description": "Performs an AJAX request with the POST HTTP method and parses the response as\nJSON notation. Requires the JSON module.",
            "itemtype": "method",
            "name": "postJSON",
            "static": 1,
            "params": [
                {
                    "name": "uri",
                    "description": "Qualified path to transaction resource.",
                    "type": "String"
                },
                {
                    "name": "options",
                    "description": "Same configuration options as Y.io.xhr()",
                    "type": "Object",
                    "optional": true
                }
            ],
            "return": {
                "description": "Promise for the response object. Contains an extra\n    `abort()` method to cancel the request.",
                "type": "Promise"
            },
            "class": "io",
            "module": "io-extras"
        },
        {
            "file": "build\\gallery-io-utils\\gallery-io-utils.js",
            "line": 268,
            "description": "Performs an AJAX request with the PUT HTTP method and parses the response as\nJSON notation. Requires the JSON module.",
            "itemtype": "method",
            "name": "putJSON",
            "static": 1,
            "params": [
                {
                    "name": "uri",
                    "description": "Qualified path to transaction resource.",
                    "type": "String"
                },
                {
                    "name": "options",
                    "description": "Same configuration options as Y.io.xhr()",
                    "type": "Object",
                    "optional": true
                }
            ],
            "return": {
                "description": "Promise for the response object. Contains an extra\n    `abort()` method to cancel the request.",
                "type": "Promise"
            },
            "class": "io",
            "module": "io-extras"
        },
        {
            "file": "build\\gallery-io-utils\\gallery-io-utils.js",
            "line": 280,
            "description": "Performs an AJAX request with the DELETE HTTP method and parses the response as\nJSON notation. Requires the JSON module.",
            "itemtype": "method",
            "name": "deleteJSON",
            "static": 1,
            "params": [
                {
                    "name": "uri",
                    "description": "Qualified path to transaction resource.",
                    "type": "String"
                },
                {
                    "name": "options",
                    "description": "Same configuration options as Y.io.xhr()",
                    "type": "Object",
                    "optional": true
                }
            ],
            "return": {
                "description": "Promise for the response object. Contains an extra\n    `abort()` method to cancel the request.",
                "type": "Promise"
            },
            "class": "io",
            "module": "io-extras"
        },
        {
            "file": "js\\io-utils.js",
            "line": 7,
            "description": "Method for initiating an ajax call.",
            "itemtype": "method",
            "name": "xhr",
            "static": 1,
            "params": [
                {
                    "name": "uri",
                    "description": "Qualified path to transaction resource.",
                    "type": "String"
                },
                {
                    "name": "options",
                    "description": "Configuration object for the transaction.",
                    "type": "Object",
                    "optional": true,
                    "props": [
                        {
                            "name": "method",
                            "description": "HTTP method verb (e.g., GET or POST).",
                            "type": "String",
                            "optional": true,
                            "optdefault": "GET"
                        },
                        {
                            "name": "data",
                            "description": "This is the name-value string that will be\n    sent as the transaction data. If the request is HTTP GET, the data become\n    part of querystring. If HTTP POST, the data are sent in the message body.",
                            "type": "Object|String",
                            "optional": true
                        },
                        {
                            "name": "form",
                            "description": "Form serialization configuration object. Its properties\n    are:\n    * `id` node object or id of HTML form\n    * `useDisabled` true to also serialize disabled form field values (defaults\n        to false)",
                            "type": "Object",
                            "optional": true
                        },
                        {
                            "name": "headers",
                            "description": "Object map of transaction headers to send to\n    the server. The object keys are the header names and the values are the\n    header values.",
                            "type": "Object",
                            "optional": true
                        },
                        {
                            "name": "timeout",
                            "description": "Millisecond threshold for the transaction\n    before being automatically aborted.",
                            "type": "Number",
                            "optional": true
                        }
                    ]
                }
            ],
            "return": {
                "description": "Promise for the response object. Contains an extra\n    `abort()` method to cancel the request.",
                "type": "Promise"
            },
            "class": "io",
            "module": "io-extras"
        },
        {
            "file": "js\\io-utils.js",
            "line": 59,
            "description": "Initiaites an AJAX call with the HTTP method GET.",
            "itemtype": "method",
            "name": "get",
            "static": 1,
            "params": [
                {
                    "name": "uri",
                    "description": "Qualified path to transaction resource.",
                    "type": "String"
                },
                {
                    "name": "options",
                    "description": "Same configuration options as Y.io.xhr()",
                    "type": "Object",
                    "optional": true
                }
            ],
            "return": {
                "description": "Promise for the response object. Contains an extra\n    `abort()` method to cancel the request.",
                "type": "Promise"
            },
            "class": "io",
            "module": "io-extras"
        },
        {
            "file": "js\\io-utils.js",
            "line": 70,
            "description": "Initiaites an AJAX call with the HTTP method POST.",
            "itemtype": "method",
            "name": "post",
            "static": 1,
            "params": [
                {
                    "name": "uri",
                    "description": "Qualified path to transaction resource.",
                    "type": "String"
                },
                {
                    "name": "options",
                    "description": "Same configuration options as Y.io.xhr()",
                    "type": "Object",
                    "optional": true
                }
            ],
            "return": {
                "description": "Promise for the response object. Contains an extra\n    `abort()` method to cancel the request.",
                "type": "Promise"
            },
            "class": "io",
            "module": "io-extras"
        },
        {
            "file": "js\\io-utils.js",
            "line": 81,
            "description": "Initiaites an AJAX call with the HTTP method PUT.",
            "itemtype": "method",
            "name": "put",
            "static": 1,
            "params": [
                {
                    "name": "uri",
                    "description": "Qualified path to transaction resource.",
                    "type": "String"
                },
                {
                    "name": "options",
                    "description": "Same configuration options as Y.io.xhr()",
                    "type": "Object",
                    "optional": true
                }
            ],
            "return": {
                "description": "Promise for the response object. Contains an extra\n    `abort()` method to cancel the request.",
                "type": "Promise"
            },
            "class": "io",
            "module": "io-extras"
        },
        {
            "file": "js\\io-utils.js",
            "line": 92,
            "description": "Initiaites an AJAX call with the HTTP method DELETE.",
            "itemtype": "method",
            "name": "delete",
            "static": 1,
            "params": [
                {
                    "name": "uri",
                    "description": "Qualified path to transaction resource.",
                    "type": "String"
                },
                {
                    "name": "options",
                    "description": "Same configuration options as Y.io.xhr()",
                    "type": "Object",
                    "optional": true
                }
            ],
            "return": {
                "description": "Promise for the response object. Contains an extra\n    `abort()` method to cancel the request.",
                "type": "Promise"
            },
            "class": "io",
            "module": "io-extras"
        },
        {
            "file": "js\\io-utils.js",
            "line": 112,
            "description": "Alias for Y.io.delete()",
            "itemtype": "method",
            "name": "DELETE",
            "static": 1,
            "deprecated": true,
            "class": "io",
            "module": "io-extras"
        },
        {
            "file": "js\\io-utils.js",
            "line": 120,
            "description": "Alias for Y.io.delete()",
            "itemtype": "method",
            "name": "del",
            "static": 1,
            "class": "io",
            "module": "io-extras"
        },
        {
            "file": "js\\io-utils.js",
            "line": 129,
            "description": "Initiaites an AJAX call with the HTTP method POST and sends the data contained\nin the specified form element.",
            "itemtype": "method",
            "name": "postForm",
            "static": 1,
            "params": [
                {
                    "name": "uri",
                    "description": "Qualified path to transaction resource.",
                    "type": "String"
                },
                {
                    "name": "selector",
                    "description": "CSS selector or Y.Node instance pointing to a form\n    element.",
                    "type": "String|Node"
                },
                {
                    "name": "options",
                    "description": "Same configuration options as Y.io.xhr()",
                    "type": "Object",
                    "optional": true
                }
            ],
            "return": {
                "description": "Promise for the response object. Contains an extra\n    `abort()` method to cancel the request.",
                "type": "Promise"
            },
            "class": "io",
            "module": "io-extras"
        },
        {
            "file": "js\\io-utils.js",
            "line": 154,
            "description": "Inserts one or more scripts tags.",
            "itemtype": "method",
            "name": "script",
            "static": 1,
            "params": [
                {
                    "name": "uri",
                    "description": "Path or array of paths to the scripts.",
                    "type": "String|String[]"
                },
                {
                    "name": "options",
                    "description": "Configuration options",
                    "type": "Object",
                    "optional": true
                }
            ],
            "return": {
                "description": "Promise for the response object.",
                "type": "Promise"
            },
            "class": "io",
            "module": "io-extras"
        },
        {
            "file": "js\\io-utils.js",
            "line": 164,
            "description": "Inserts one or more CSS files into the page.",
            "itemtype": "method",
            "name": "css",
            "static": 1,
            "params": [
                {
                    "name": "uri",
                    "description": "Path or array of paths to the CSS files.",
                    "type": "String|String[]"
                },
                {
                    "name": "options",
                    "description": "Configuration options",
                    "type": "Object",
                    "optional": true
                }
            ],
            "return": {
                "description": "Promise for the response object.",
                "type": "Promise"
            },
            "class": "io",
            "module": "io-extras"
        },
        {
            "file": "js\\io-utils.js",
            "line": 188,
            "description": "Performs a JSONP request. Requires the JSONP module.",
            "itemtype": "method",
            "name": "jsonp",
            "static": 1,
            "params": [
                {
                    "name": "uri",
                    "description": "The url of the JSONP service with the {callback}\n    placeholder where the callback function name typically goes",
                    "type": "String"
                },
                {
                    "name": "options",
                    "description": "Configuration options for the request",
                    "type": "Object",
                    "optional": true,
                    "props": [
                        {
                            "name": "timeout",
                            "description": "Millisecond threshold for the transaction\n    before being automatically aborted",
                            "type": "Number",
                            "optional": true
                        },
                        {
                            "name": "format",
                            "description": "Preprocessor function to stitch together\n    the supplied URL (first argument), the proxy function name (internally\n    generated), and any additional arguments passed to JSONPRequest#send()",
                            "type": "Function",
                            "optional": true
                        }
                    ]
                }
            ],
            "return": {
                "description": "Promise for the response object.",
                "type": "Promise"
            },
            "class": "io",
            "module": "io-extras"
        },
        {
            "file": "js\\io-utils.js",
            "line": 227,
            "description": "Performs an AJAX request and parses the response as JSON notation.\nRequires the JSON module.",
            "itemtype": "method",
            "name": "json",
            "static": 1,
            "params": [
                {
                    "name": "uri",
                    "description": "Qualified path to transaction resource.",
                    "type": "String"
                },
                {
                    "name": "options",
                    "description": "Same configuration options as Y.io.xhr()",
                    "type": "Object",
                    "optional": true
                }
            ],
            "return": {
                "description": "Promise for the response object. Contains an extra\n    `abort()` method to cancel the request.",
                "type": "Promise"
            },
            "class": "io",
            "module": "io-extras"
        },
        {
            "file": "js\\io-utils.js",
            "line": 250,
            "description": "Performs an AJAX request with the GET HTTP method and parses the response as\nJSON notation. Requires the JSON module.",
            "itemtype": "method",
            "name": "getJSON",
            "static": 1,
            "params": [
                {
                    "name": "uri",
                    "description": "Qualified path to transaction resource.",
                    "type": "String"
                },
                {
                    "name": "options",
                    "description": "Same configuration options as Y.io.xhr()",
                    "type": "Object",
                    "optional": true
                }
            ],
            "return": {
                "description": "Promise for the response object. Contains an extra\n    `abort()` method to cancel the request.",
                "type": "Promise"
            },
            "class": "io",
            "module": "io-extras"
        },
        {
            "file": "js\\io-utils.js",
            "line": 262,
            "description": "Performs an AJAX request with the POST HTTP method and parses the response as\nJSON notation. Requires the JSON module.",
            "itemtype": "method",
            "name": "postJSON",
            "static": 1,
            "params": [
                {
                    "name": "uri",
                    "description": "Qualified path to transaction resource.",
                    "type": "String"
                },
                {
                    "name": "options",
                    "description": "Same configuration options as Y.io.xhr()",
                    "type": "Object",
                    "optional": true
                }
            ],
            "return": {
                "description": "Promise for the response object. Contains an extra\n    `abort()` method to cancel the request.",
                "type": "Promise"
            },
            "class": "io",
            "module": "io-extras"
        },
        {
            "file": "js\\io-utils.js",
            "line": 274,
            "description": "Performs an AJAX request with the PUT HTTP method and parses the response as\nJSON notation. Requires the JSON module.",
            "itemtype": "method",
            "name": "putJSON",
            "static": 1,
            "params": [
                {
                    "name": "uri",
                    "description": "Qualified path to transaction resource.",
                    "type": "String"
                },
                {
                    "name": "options",
                    "description": "Same configuration options as Y.io.xhr()",
                    "type": "Object",
                    "optional": true
                }
            ],
            "return": {
                "description": "Promise for the response object. Contains an extra\n    `abort()` method to cancel the request.",
                "type": "Promise"
            },
            "class": "io",
            "module": "io-extras"
        },
        {
            "file": "js\\io-utils.js",
            "line": 286,
            "description": "Performs an AJAX request with the DELETE HTTP method and parses the response as\nJSON notation. Requires the JSON module.",
            "itemtype": "method",
            "name": "deleteJSON",
            "static": 1,
            "params": [
                {
                    "name": "uri",
                    "description": "Qualified path to transaction resource.",
                    "type": "String"
                },
                {
                    "name": "options",
                    "description": "Same configuration options as Y.io.xhr()",
                    "type": "Object",
                    "optional": true
                }
            ],
            "return": {
                "description": "Promise for the response object. Contains an extra\n    `abort()` method to cancel the request.",
                "type": "Promise"
            },
            "class": "io",
            "module": "io-extras"
        }
    ],
    "warnings": []
}